squeak/__init__.py
squeak/messages.py
squeak/net.py
squeak/params.py
squeak/core/__init__.py
squeak/core/_script.py
squeak/core/elliptic.py
squeak/core/encryption.py
squeak/core/hashing.py
squeak/core/script.py
squeak/core/signing.py
squeakpy-0.7.7.dist-info/LICENSE
squeakpy-0.7.7.dist-info/METADATA
squeakpy-0.7.7.dist-info/WHEEL
squeakpy-0.7.7.dist-info/top_level.txt
squeakpy-0.7.7.dist-info/zip-safe
squeakpy-0.7.7.dist-info/RECORD
